{
  "kind": "collectionType",
  "collectionName": "presses",
  "info": {
    "singularName": "press",
    "pluralName": "presses",
    "displayName": "Press"
  },
  "options": {
    "draftAndPublish": true
  },
  "pluginOptions": {
    "i18n": {
      "localized": true
    }
  },
  "attributes": {
    "title": {
      "type": "string",
      "pluginOptions": {
        "i18n": {
          "localized": true
        }
      },
      "maxLength": 100,
      "required": true,
      "unique": true
    },
    "link": {
      "type": "string",
      "pluginOptions": {
        "i18n": {
          "localized": true
        }
      },
      "required": true,
      "unique": false
    },
    "image": {
      "type": "media",
      "pluginOptions": {
        "i18n": {
          "localized": true
        }
      },
      "multiple": false,
      "required": true,
      "allowedTypes": [
        "images",
        "files",
        "videos"
      ]
    }
  }
}
